LICENSE.md
README.md
setup.cfg
setup.py
rpiTempMod/RpiTempmonGraph.py
rpiTempMod/RpiTempmonWork.py
rpiTempMod/__init__.py
rpiTempSrc/__init__.py
rpiTempSrc/rpi_tempmon.py
rpi_tempmon.py.egg-info/PKG-INFO
rpi_tempmon.py.egg-info/SOURCES.txt
rpi_tempmon.py.egg-info/dependency_links.txt
rpi_tempmon.py.egg-info/requires.txt
rpi_tempmon.py.egg-info/top_level.txt